MANIFEST.in
README.markdown
pro.py
setup.py
bin/pro
pro.egg-info/PKG-INFO
pro.egg-info/SOURCES.txt
pro.egg-info/dependency_links.txt
pro.egg-info/top_level.txt