Metadata-Version: 1.0
Name: pro
Version: 0.1.2
Summary: UNKNOWN
Home-page: UNKNOWN
Author: Gabriel Grant
Author-email: g@briel.ca
License: LGPL
Platform: UNKNOWN
